[{"name":"abstract fun build(): SmartAdapter<T>","description":"com.ayvytr.adapter.internal.SmartAdapterBuilder.build","location":"smart-adapter-androidx/com.ayvytr.adapter.internal/-smart-adapter-builder/build.html","searchKeys":["build","abstract fun build(): SmartAdapter<T>","com.ayvytr.adapter.internal.SmartAdapterBuilder.build"]},{"name":"abstract fun diff(smartDiffCallback: SmartDiffCallback<T> = SmartDiffCallback(), detectMovies: Boolean = true)","description":"com.ayvytr.adapter.internal.SmartAdapterBuilder.diff","location":"smart-adapter-androidx/com.ayvytr.adapter.internal/-smart-adapter-builder/diff.html","searchKeys":["diff","abstract fun diff(smartDiffCallback: SmartDiffCallback<T> = SmartDiffCallback(), detectMovies: Boolean = true)","com.ayvytr.adapter.internal.SmartAdapterBuilder.diff"]},{"name":"abstract var itemClick: (item: T, position: Int) -> Unit","description":"com.ayvytr.adapter.internal.SmartAdapterBuilder.itemClick","location":"smart-adapter-androidx/com.ayvytr.adapter.internal/-smart-adapter-builder/item-click.html","searchKeys":["itemClick","abstract var itemClick: (item: T, position: Int) -> Unit","com.ayvytr.adapter.internal.SmartAdapterBuilder.itemClick"]},{"name":"abstract var itemLongClick: (item: T, position: Int) -> Unit","description":"com.ayvytr.adapter.internal.SmartAdapterBuilder.itemLongClick","location":"smart-adapter-androidx/com.ayvytr.adapter.internal/-smart-adapter-builder/item-long-click.html","searchKeys":["itemLongClick","abstract var itemLongClick: (item: T, position: Int) -> Unit","com.ayvytr.adapter.internal.SmartAdapterBuilder.itemLongClick"]},{"name":"abstract var itemViewOf: SmartContainer<T>","description":"com.ayvytr.adapter.internal.SmartAdapterBuilder.itemViewOf","location":"smart-adapter-androidx/com.ayvytr.adapter.internal/-smart-adapter-builder/item-view-of.html","searchKeys":["itemViewOf","abstract var itemViewOf: SmartContainer<T>","com.ayvytr.adapter.internal.SmartAdapterBuilder.itemViewOf"]},{"name":"abstract var items: List<T>","description":"com.ayvytr.adapter.internal.SmartAdapterBuilder.items","location":"smart-adapter-androidx/com.ayvytr.adapter.internal/-smart-adapter-builder/items.html","searchKeys":["items","abstract var items: List<T>","com.ayvytr.adapter.internal.SmartAdapterBuilder.items"]},{"name":"abstract var multiItemViewOf: List<SmartContainer<T>>","description":"com.ayvytr.adapter.internal.SmartAdapterBuilder.multiItemViewOf","location":"smart-adapter-androidx/com.ayvytr.adapter.internal/-smart-adapter-builder/multi-item-view-of.html","searchKeys":["multiItemViewOf","abstract var multiItemViewOf: List<SmartContainer<T>>","com.ayvytr.adapter.internal.SmartAdapterBuilder.multiItemViewOf"]},{"name":"abstract var type: (it: T) -> Int","description":"com.ayvytr.adapter.internal.SmartAdapterBuilder.type","location":"smart-adapter-androidx/com.ayvytr.adapter.internal/-smart-adapter-builder/type.html","searchKeys":["type","abstract var type: (it: T) -> Int","com.ayvytr.adapter.internal.SmartAdapterBuilder.type"]},{"name":"abstract var typePosition: (it: T, position: Int) -> Int","description":"com.ayvytr.adapter.internal.SmartAdapterBuilder.typePosition","location":"smart-adapter-androidx/com.ayvytr.adapter.internal/-smart-adapter-builder/type-position.html","searchKeys":["typePosition","abstract var typePosition: (it: T, position: Int) -> Int","com.ayvytr.adapter.internal.SmartAdapterBuilder.typePosition"]},{"name":"class SmartViewHolder<T>(containerView: View, val viewType: Int, smartContainer: SmartContainer<T>) : RecyclerView.ViewHolder","description":"com.ayvytr.adapter.SmartViewHolder","location":"smart-adapter-androidx/com.ayvytr.adapter/-smart-view-holder/index.html","searchKeys":["SmartViewHolder","class SmartViewHolder<T>(containerView: View, val viewType: Int, smartContainer: SmartContainer<T>) : RecyclerView.ViewHolder","com.ayvytr.adapter.SmartViewHolder"]},{"name":"const val NO_GETTER: String","description":"com.ayvytr.adapter.internal.Internals.NO_GETTER","location":"smart-adapter-androidx/com.ayvytr.adapter.internal/-internals/-n-o_-g-e-t-t-e-r.html","searchKeys":["NO_GETTER","const val NO_GETTER: String","com.ayvytr.adapter.internal.Internals.NO_GETTER"]},{"name":"constructor()","description":"com.ayvytr.adapter.SmartDiffCallback.SmartDiffCallback","location":"smart-adapter-androidx/com.ayvytr.adapter/-smart-diff-callback/-smart-diff-callback.html","searchKeys":["SmartDiffCallback","constructor()","com.ayvytr.adapter.SmartDiffCallback.SmartDiffCallback"]},{"name":"constructor(containerView: View, viewType: Int, smartContainer: SmartContainer<T>)","description":"com.ayvytr.adapter.SmartViewHolder.SmartViewHolder","location":"smart-adapter-androidx/com.ayvytr.adapter/-smart-view-holder/-smart-view-holder.html","searchKeys":["SmartViewHolder","constructor(containerView: View, viewType: Int, smartContainer: SmartContainer<T>)","com.ayvytr.adapter.SmartViewHolder.SmartViewHolder"]},{"name":"constructor(layoutId: Int, viewType: Int, bind: View.(item: T, position: Int) -> Unit)","description":"com.ayvytr.adapter.SmartContainer.SmartContainer","location":"smart-adapter-androidx/com.ayvytr.adapter/-smart-container/-smart-container.html","searchKeys":["SmartContainer","constructor(layoutId: Int, viewType: Int, bind: View.(item: T, position: Int) -> Unit)","com.ayvytr.adapter.SmartContainer.SmartContainer"]},{"name":"constructor(list: MutableList<T> = mutableListOf(), bind: SmartContainer<T>? = null)","description":"com.ayvytr.adapter.SmartAdapter.SmartAdapter","location":"smart-adapter-androidx/com.ayvytr.adapter/-smart-adapter/-smart-adapter.html","searchKeys":["SmartAdapter","constructor(list: MutableList<T> = mutableListOf(), bind: SmartContainer<T>? = null)","com.ayvytr.adapter.SmartAdapter.SmartAdapter"]},{"name":"fun <T> Context.smart(init: SmartAdapterBuilder<T>.() -> Unit): SmartAdapter<T>","description":"com.ayvytr.adapter.smart","location":"smart-adapter-androidx/com.ayvytr.adapter/smart.html","searchKeys":["smart","fun <T> Context.smart(init: SmartAdapterBuilder<T>.() -> Unit): SmartAdapter<T>","com.ayvytr.adapter.smart"]},{"name":"fun <T> Context.smart(list: List<T>, layoutId: Int, bind: View.(item: T, position: Int) -> Unit, init: SmartAdapterBuilder<T>.() -> Unit): SmartAdapter<T>","description":"com.ayvytr.adapter.smart","location":"smart-adapter-androidx/com.ayvytr.adapter/smart.html","searchKeys":["smart","fun <T> Context.smart(list: List<T>, layoutId: Int, bind: View.(item: T, position: Int) -> Unit, init: SmartAdapterBuilder<T>.() -> Unit): SmartAdapter<T>","com.ayvytr.adapter.smart"]},{"name":"fun <T> Fragment.smart(init: SmartAdapterBuilder<T>.() -> Unit): SmartAdapter<T>","description":"com.ayvytr.adapter.smart","location":"smart-adapter-androidx/com.ayvytr.adapter/smart.html","searchKeys":["smart","fun <T> Fragment.smart(init: SmartAdapterBuilder<T>.() -> Unit): SmartAdapter<T>","com.ayvytr.adapter.smart"]},{"name":"fun <T> Fragment.smart(list: List<T>, layoutId: Int, bind: View.(item: T, position: Int) -> Unit, init: SmartAdapterBuilder<T>.() -> Unit): SmartAdapter<T>","description":"com.ayvytr.adapter.smart","location":"smart-adapter-androidx/com.ayvytr.adapter/smart.html","searchKeys":["smart","fun <T> Fragment.smart(list: List<T>, layoutId: Int, bind: View.(item: T, position: Int) -> Unit, init: SmartAdapterBuilder<T>.() -> Unit): SmartAdapter<T>","com.ayvytr.adapter.smart"]},{"name":"fun add(item: T, index: Int = list.size)","description":"com.ayvytr.adapter.SmartAdapter.add","location":"smart-adapter-androidx/com.ayvytr.adapter/-smart-adapter/add.html","searchKeys":["add","fun add(item: T, index: Int = list.size)","com.ayvytr.adapter.SmartAdapter.add"]},{"name":"fun addAll(items: List<T>, index: Int = list.size)","description":"com.ayvytr.adapter.SmartAdapter.addAll","location":"smart-adapter-androidx/com.ayvytr.adapter/-smart-adapter/add-all.html","searchKeys":["addAll","fun addAll(items: List<T>, index: Int = list.size)","com.ayvytr.adapter.SmartAdapter.addAll"]},{"name":"fun bind(t: T, position: Int, bind: View.(item: T, position: Int) -> Unit = smartContainer.bind)","description":"com.ayvytr.adapter.SmartViewHolder.bind","location":"smart-adapter-androidx/com.ayvytr.adapter/-smart-view-holder/bind.html","searchKeys":["bind","fun bind(t: T, position: Int, bind: View.(item: T, position: Int) -> Unit = smartContainer.bind)","com.ayvytr.adapter.SmartViewHolder.bind"]},{"name":"fun clear()","description":"com.ayvytr.adapter.SmartAdapter.clear","location":"smart-adapter-androidx/com.ayvytr.adapter/-smart-adapter/clear.html","searchKeys":["clear","fun clear()","com.ayvytr.adapter.SmartAdapter.clear"]},{"name":"fun click(onItemClickListener: (item: T, position: Int) -> Unit): SmartAdapter<T>","description":"com.ayvytr.adapter.SmartAdapter.click","location":"smart-adapter-androidx/com.ayvytr.adapter/-smart-adapter/click.html","searchKeys":["click","fun click(onItemClickListener: (item: T, position: Int) -> Unit): SmartAdapter<T>","com.ayvytr.adapter.SmartAdapter.click"]},{"name":"fun hasDiff(): Boolean","description":"com.ayvytr.adapter.SmartAdapter.hasDiff","location":"smart-adapter-androidx/com.ayvytr.adapter/-smart-adapter/has-diff.html","searchKeys":["hasDiff","fun hasDiff(): Boolean","com.ayvytr.adapter.SmartAdapter.hasDiff"]},{"name":"fun isEmpty(): Boolean","description":"com.ayvytr.adapter.SmartAdapter.isEmpty","location":"smart-adapter-androidx/com.ayvytr.adapter/-smart-adapter/is-empty.html","searchKeys":["isEmpty","fun isEmpty(): Boolean","com.ayvytr.adapter.SmartAdapter.isEmpty"]},{"name":"fun longClick(onItemLongClickListener: (item: T, position: Int) -> Unit): SmartAdapter<T>","description":"com.ayvytr.adapter.SmartAdapter.longClick","location":"smart-adapter-androidx/com.ayvytr.adapter/-smart-adapter/long-click.html","searchKeys":["longClick","fun longClick(onItemLongClickListener: (item: T, position: Int) -> Unit): SmartAdapter<T>","com.ayvytr.adapter.SmartAdapter.longClick"]},{"name":"fun noGetter(): Nothing","description":"com.ayvytr.adapter.internal.Internals.noGetter","location":"smart-adapter-androidx/com.ayvytr.adapter.internal/-internals/no-getter.html","searchKeys":["noGetter","fun noGetter(): Nothing","com.ayvytr.adapter.internal.Internals.noGetter"]},{"name":"fun remove(item: T): Boolean","description":"com.ayvytr.adapter.SmartAdapter.remove","location":"smart-adapter-androidx/com.ayvytr.adapter/-smart-adapter/remove.html","searchKeys":["remove","fun remove(item: T): Boolean","com.ayvytr.adapter.SmartAdapter.remove"]},{"name":"fun removeAll(items: List<T>)","description":"com.ayvytr.adapter.SmartAdapter.removeAll","location":"smart-adapter-androidx/com.ayvytr.adapter/-smart-adapter/remove-all.html","searchKeys":["removeAll","fun removeAll(items: List<T>)","com.ayvytr.adapter.SmartAdapter.removeAll"]},{"name":"fun removeAt(index: Int)","description":"com.ayvytr.adapter.SmartAdapter.removeAt","location":"smart-adapter-androidx/com.ayvytr.adapter/-smart-adapter/remove-at.html","searchKeys":["removeAt","fun removeAt(index: Int)","com.ayvytr.adapter.SmartAdapter.removeAt"]},{"name":"fun removeDiff()","description":"com.ayvytr.adapter.SmartAdapter.removeDiff","location":"smart-adapter-androidx/com.ayvytr.adapter/-smart-adapter/remove-diff.html","searchKeys":["removeDiff","fun removeDiff()","com.ayvytr.adapter.SmartAdapter.removeDiff"]},{"name":"fun type(predicate: (item: T, position: Int) -> Int): SmartAdapter<T>","description":"com.ayvytr.adapter.SmartAdapter.type","location":"smart-adapter-androidx/com.ayvytr.adapter/-smart-adapter/type.html","searchKeys":["type","fun type(predicate: (item: T, position: Int) -> Int): SmartAdapter<T>","com.ayvytr.adapter.SmartAdapter.type"]},{"name":"fun update(newList: List<T>, isAppend: Boolean = false, isAppendToHead: Boolean = false)","description":"com.ayvytr.adapter.SmartAdapter.update","location":"smart-adapter-androidx/com.ayvytr.adapter/-smart-adapter/update.html","searchKeys":["update","fun update(newList: List<T>, isAppend: Boolean = false, isAppendToHead: Boolean = false)","com.ayvytr.adapter.SmartAdapter.update"]},{"name":"interface SmartAdapterBuilder<T>","description":"com.ayvytr.adapter.internal.SmartAdapterBuilder","location":"smart-adapter-androidx/com.ayvytr.adapter.internal/-smart-adapter-builder/index.html","searchKeys":["SmartAdapterBuilder","interface SmartAdapterBuilder<T>","com.ayvytr.adapter.internal.SmartAdapterBuilder"]},{"name":"object Internals","description":"com.ayvytr.adapter.internal.Internals","location":"smart-adapter-androidx/com.ayvytr.adapter.internal/-internals/index.html","searchKeys":["Internals","object Internals","com.ayvytr.adapter.internal.Internals"]},{"name":"open class SmartAdapter<T>(val list: MutableList<T> = mutableListOf(), bind: SmartContainer<T>? = null) : RecyclerView.Adapter<SmartViewHolder<T>> ","description":"com.ayvytr.adapter.SmartAdapter","location":"smart-adapter-androidx/com.ayvytr.adapter/-smart-adapter/index.html","searchKeys":["SmartAdapter","open class SmartAdapter<T>(val list: MutableList<T> = mutableListOf(), bind: SmartContainer<T>? = null) : RecyclerView.Adapter<SmartViewHolder<T>> ","com.ayvytr.adapter.SmartAdapter"]},{"name":"open class SmartContainer<T>(val layoutId: Int, val viewType: Int, val bind: View.(item: T, position: Int) -> Unit)","description":"com.ayvytr.adapter.SmartContainer","location":"smart-adapter-androidx/com.ayvytr.adapter/-smart-container/index.html","searchKeys":["SmartContainer","open class SmartContainer<T>(val layoutId: Int, val viewType: Int, val bind: View.(item: T, position: Int) -> Unit)","com.ayvytr.adapter.SmartContainer"]},{"name":"open class SmartDiffCallback<T>","description":"com.ayvytr.adapter.SmartDiffCallback","location":"smart-adapter-androidx/com.ayvytr.adapter/-smart-diff-callback/index.html","searchKeys":["SmartDiffCallback","open class SmartDiffCallback<T>","com.ayvytr.adapter.SmartDiffCallback"]},{"name":"open fun areContentsTheSame(oldItem: T, newItem: T): Boolean","description":"com.ayvytr.adapter.SmartDiffCallback.areContentsTheSame","location":"smart-adapter-androidx/com.ayvytr.adapter/-smart-diff-callback/are-contents-the-same.html","searchKeys":["areContentsTheSame","open fun areContentsTheSame(oldItem: T, newItem: T): Boolean","com.ayvytr.adapter.SmartDiffCallback.areContentsTheSame"]},{"name":"open fun areItemsTheSame(oldItem: T, newItem: T): Boolean","description":"com.ayvytr.adapter.SmartDiffCallback.areItemsTheSame","location":"smart-adapter-androidx/com.ayvytr.adapter/-smart-diff-callback/are-items-the-same.html","searchKeys":["areItemsTheSame","open fun areItemsTheSame(oldItem: T, newItem: T): Boolean","com.ayvytr.adapter.SmartDiffCallback.areItemsTheSame"]},{"name":"open fun diff(smartDiffCallback: SmartDiffCallback<T>? = SmartDiffCallback(), detectMovies: Boolean = true): SmartAdapter<T>","description":"com.ayvytr.adapter.SmartAdapter.diff","location":"smart-adapter-androidx/com.ayvytr.adapter/-smart-adapter/diff.html","searchKeys":["diff","open fun diff(smartDiffCallback: SmartDiffCallback<T>? = SmartDiffCallback(), detectMovies: Boolean = true): SmartAdapter<T>","com.ayvytr.adapter.SmartAdapter.diff"]},{"name":"open fun getChangePayload(oldItem: T, newItem: T): Any?","description":"com.ayvytr.adapter.SmartDiffCallback.getChangePayload","location":"smart-adapter-androidx/com.ayvytr.adapter/-smart-diff-callback/get-change-payload.html","searchKeys":["getChangePayload","open fun getChangePayload(oldItem: T, newItem: T): Any?","com.ayvytr.adapter.SmartDiffCallback.getChangePayload"]},{"name":"open fun map(layoutId: Int, type: Int, bind: View.(item: T, position: Int) -> Unit): SmartAdapter<T>","description":"com.ayvytr.adapter.SmartAdapter.map","location":"smart-adapter-androidx/com.ayvytr.adapter/-smart-adapter/map.html","searchKeys":["map","open fun map(layoutId: Int, type: Int, bind: View.(item: T, position: Int) -> Unit): SmartAdapter<T>","com.ayvytr.adapter.SmartAdapter.map"]},{"name":"open fun map(smartContainer: SmartContainer<T>): SmartAdapter<T>","description":"com.ayvytr.adapter.SmartAdapter.map","location":"smart-adapter-androidx/com.ayvytr.adapter/-smart-adapter/map.html","searchKeys":["map","open fun map(smartContainer: SmartContainer<T>): SmartAdapter<T>","com.ayvytr.adapter.SmartAdapter.map"]},{"name":"open fun onBindPayloads(holder: SmartViewHolder<T>, item: T, position: Int, payloads: List<Any>)","description":"com.ayvytr.adapter.SmartDiffCallback.onBindPayloads","location":"smart-adapter-androidx/com.ayvytr.adapter/-smart-diff-callback/on-bind-payloads.html","searchKeys":["onBindPayloads","open fun onBindPayloads(holder: SmartViewHolder<T>, item: T, position: Int, payloads: List<Any>)","com.ayvytr.adapter.SmartDiffCallback.onBindPayloads"]},{"name":"open override fun getItemCount(): Int","description":"com.ayvytr.adapter.SmartAdapter.getItemCount","location":"smart-adapter-androidx/com.ayvytr.adapter/-smart-adapter/get-item-count.html","searchKeys":["getItemCount","open override fun getItemCount(): Int","com.ayvytr.adapter.SmartAdapter.getItemCount"]},{"name":"open override fun getItemViewType(position: Int): Int","description":"com.ayvytr.adapter.SmartAdapter.getItemViewType","location":"smart-adapter-androidx/com.ayvytr.adapter/-smart-adapter/get-item-view-type.html","searchKeys":["getItemViewType","open override fun getItemViewType(position: Int): Int","com.ayvytr.adapter.SmartAdapter.getItemViewType"]},{"name":"open override fun onBindViewHolder(holder: SmartViewHolder<T>, position: Int)","description":"com.ayvytr.adapter.SmartAdapter.onBindViewHolder","location":"smart-adapter-androidx/com.ayvytr.adapter/-smart-adapter/on-bind-view-holder.html","searchKeys":["onBindViewHolder","open override fun onBindViewHolder(holder: SmartViewHolder<T>, position: Int)","com.ayvytr.adapter.SmartAdapter.onBindViewHolder"]},{"name":"open override fun onBindViewHolder(holder: SmartViewHolder<T>, position: Int, payloads: MutableList<Any>)","description":"com.ayvytr.adapter.SmartAdapter.onBindViewHolder","location":"smart-adapter-androidx/com.ayvytr.adapter/-smart-adapter/on-bind-view-holder.html","searchKeys":["onBindViewHolder","open override fun onBindViewHolder(holder: SmartViewHolder<T>, position: Int, payloads: MutableList<Any>)","com.ayvytr.adapter.SmartAdapter.onBindViewHolder"]},{"name":"open override fun onCreateViewHolder(parent: ViewGroup, viewType: Int): SmartViewHolder<T>","description":"com.ayvytr.adapter.SmartAdapter.onCreateViewHolder","location":"smart-adapter-androidx/com.ayvytr.adapter/-smart-adapter/on-create-view-holder.html","searchKeys":["onCreateViewHolder","open override fun onCreateViewHolder(parent: ViewGroup, viewType: Int): SmartViewHolder<T>","com.ayvytr.adapter.SmartAdapter.onCreateViewHolder"]},{"name":"open override fun toString(): String","description":"com.ayvytr.adapter.SmartContainer.toString","location":"smart-adapter-androidx/com.ayvytr.adapter/-smart-container/to-string.html","searchKeys":["toString","open override fun toString(): String","com.ayvytr.adapter.SmartContainer.toString"]},{"name":"open override val itemCount: Int","description":"com.ayvytr.adapter.SmartAdapter.itemCount","location":"smart-adapter-androidx/com.ayvytr.adapter/-smart-adapter/item-count.html","searchKeys":["itemCount","open override val itemCount: Int","com.ayvytr.adapter.SmartAdapter.itemCount"]},{"name":"val bind: View.(item: T, position: Int) -> Unit","description":"com.ayvytr.adapter.SmartContainer.bind","location":"smart-adapter-androidx/com.ayvytr.adapter/-smart-container/bind.html","searchKeys":["bind","val bind: View.(item: T, position: Int) -> Unit","com.ayvytr.adapter.SmartContainer.bind"]},{"name":"val layoutId: Int","description":"com.ayvytr.adapter.SmartContainer.layoutId","location":"smart-adapter-androidx/com.ayvytr.adapter/-smart-container/layout-id.html","searchKeys":["layoutId","val layoutId: Int","com.ayvytr.adapter.SmartContainer.layoutId"]},{"name":"val list: MutableList<T>","description":"com.ayvytr.adapter.SmartAdapter.list","location":"smart-adapter-androidx/com.ayvytr.adapter/-smart-adapter/list.html","searchKeys":["list","val list: MutableList<T>","com.ayvytr.adapter.SmartAdapter.list"]},{"name":"val viewType: Int","description":"com.ayvytr.adapter.SmartContainer.viewType","location":"smart-adapter-androidx/com.ayvytr.adapter/-smart-container/view-type.html","searchKeys":["viewType","val viewType: Int","com.ayvytr.adapter.SmartContainer.viewType"]},{"name":"val viewType: Int","description":"com.ayvytr.adapter.SmartViewHolder.viewType","location":"smart-adapter-androidx/com.ayvytr.adapter/-smart-view-holder/view-type.html","searchKeys":["viewType","val viewType: Int","com.ayvytr.adapter.SmartViewHolder.viewType"]},{"name":"var detectMovies: Boolean","description":"com.ayvytr.adapter.SmartAdapter.detectMovies","location":"smart-adapter-androidx/com.ayvytr.adapter/-smart-adapter/detect-movies.html","searchKeys":["detectMovies","var detectMovies: Boolean","com.ayvytr.adapter.SmartAdapter.detectMovies"]},{"name":"var diffCallback: DiffUtil.Callback?","description":"com.ayvytr.adapter.SmartAdapter.diffCallback","location":"smart-adapter-androidx/com.ayvytr.adapter/-smart-adapter/diff-callback.html","searchKeys":["diffCallback","var diffCallback: DiffUtil.Callback?","com.ayvytr.adapter.SmartAdapter.diffCallback"]},{"name":"var itemClickListener: (T, Int) -> Unit","description":"com.ayvytr.adapter.SmartAdapter.itemClickListener","location":"smart-adapter-androidx/com.ayvytr.adapter/-smart-adapter/item-click-listener.html","searchKeys":["itemClickListener","var itemClickListener: (T, Int) -> Unit","com.ayvytr.adapter.SmartAdapter.itemClickListener"]},{"name":"var itemLongClickListener: (T, Int) -> Unit","description":"com.ayvytr.adapter.SmartAdapter.itemLongClickListener","location":"smart-adapter-androidx/com.ayvytr.adapter/-smart-adapter/item-long-click-listener.html","searchKeys":["itemLongClickListener","var itemLongClickListener: (T, Int) -> Unit","com.ayvytr.adapter.SmartAdapter.itemLongClickListener"]}]